camouflage/__init__.py
camouflage/adapters.py
camouflage/anonymizer.py
camouflage/deanonymizer.py
camouflage/registry.py
camouflage/transform.py
camouflage/utils.py
camouflage/facets/__init__.py
camouflage/facets/age.py
camouflage/facets/amount.py
camouflage/facets/country.py
camouflage/facets/datetime.py
camouflage/facets/ipv4.py
camouflage/facets/user_agent.py
camouflage-1.0.5.dist-info/licenses/LICENSE
camouflage-1.0.5.dist-info/METADATA
camouflage-1.0.5.dist-info/WHEEL
camouflage-1.0.5.dist-info/top_level.txt
camouflage-1.0.5.dist-info/RECORD
