Metadata-Version: 2.4
Name: camouflage
Version: 1.0.5
Summary: Camouflage library, reversible data anonymization
Author-email: Nazar Kalinichenko <kalinichenko@dataminder.ai>
Maintainer-email: Nazar Kalinichenko <kalinichenko@dataminder.ai>
License-Expression: MIT
Project-URL: Repository, https://github.com/data-minder/camouflage
Project-URL: Issues, https://github.com/data-minder/camouflage/issues
Keywords: anonymization,data-anonymization,data-masking,data-protection,privacy,security
Classifier: Development Status :: 3 - Alpha
Classifier: Programming Language :: Python :: 3
Classifier: Operating System :: OS Independent
Requires-Python: >=3.8
License-File: LICENSE
Requires-Dist: Faker~=37.0
Requires-Dist: pandas~=2.0
Dynamic: license-file
